mathboard/__init__.py
mathboard/module.py
mathboard/test/__init__.py
mathboard/test/test.py
mathboard-0.1.0.dist-info/LICENSE.txt
mathboard-0.1.0.dist-info/METADATA
mathboard-0.1.0.dist-info/WHEEL
mathboard-0.1.0.dist-info/top_level.txt
mathboard-0.1.0.dist-info/RECORD
